xingen/__init__.py
xingen/server.py
xingen/coreplugins/admin/__init__.py
xingen/coreplugins/admin/agent_importer.py
xingen/coreplugins/admin/agent_router.py
xingen/coreplugins/admin/command_router.py
xingen/coreplugins/admin/persona_router.py
xingen/coreplugins/admin/plugin_manager.py
xingen/coreplugins/admin/plugin_router.py
xingen/coreplugins/admin/router.py
xingen/coreplugins/admin/settings_router.py
xingen/coreplugins/agent/agent.py
xingen/coreplugins/agent/command_parser.py
xingen/coreplugins/agent/ensure_msg_type.py
xingen/coreplugins/agent/system.j2
xingen/coreplugins/chat/__init__.py
xingen/coreplugins/chat/commands.py
xingen/coreplugins/chat/format_result_msgs.py
xingen/coreplugins/chat/mod.py
xingen/coreplugins/chat/models.py
xingen/coreplugins/chat/router.py
xingen/coreplugins/chat/services.py
xingen/coreplugins/chat/utils.py
xingen/coreplugins/home/mod.py
xingen/coreplugins/home/router.py
xingen/coreplugins/jwt_auth/__init__.py
xingen/coreplugins/jwt_auth/middleware.py
xingen/coreplugins/jwt_auth/mod.py
xingen/coreplugins/jwt_auth/router.py
xingen/coreplugins/login/mod.py
xingen/coreplugins/login/router.py
xingen/coreplugins/persona/__init__.py
xingen/coreplugins/persona/mod.py
xingen/coreplugins/startup/__init__.py
xingen/coreplugins/startup/mod.py
xingen/lib/__init__.py
xingen/lib/chatcontext.py
xingen/lib/chatlog.py
xingen/lib/json_escape.py
xingen/lib/model_selector.py
xingen/lib/plugins.py
xingen/lib/plugins_install.py
xingen/lib/route_decorators.py
xingen/lib/templates.py
xingen/lib/db/organize_models.py
xingen/lib/db/preferences.py
xingen/lib/json_str_block/__init__.py
xingen/lib/json_str_block/json_str_block.py
xingen/lib/logging/log_router.py
xingen/lib/logging/logfiles.py
xingen/lib/pipelines/pipe.py
xingen/lib/pipelines/pipelines.py
xingen/lib/providers/__init__.py
xingen/lib/providers/commands.py
xingen/lib/providers/hooks.py
xingen/lib/providers/services.py
xingen/lib/utils/check_args.py
xingen/lib/utils/dataurl.py
xingen-0.1.0.dist-info/LICENSE
xingen-0.1.0.dist-info/METADATA
xingen-0.1.0.dist-info/WHEEL
xingen-0.1.0.dist-info/entry_points.txt
xingen-0.1.0.dist-info/top_level.txt
xingen-0.1.0.dist-info/RECORD
